mediathekDownloader/__init__.py
mediathekDownloader/__main__.py
mediathekDownloader/downloadQueueItem.py
mediathekDownloader/vsMetaInfoGenerator.py
mediathekDownloader-1.0.2.dist-info/LICENSE
mediathekDownloader-1.0.2.dist-info/METADATA
mediathekDownloader-1.0.2.dist-info/WHEEL
mediathekDownloader-1.0.2.dist-info/top_level.txt
mediathekDownloader-1.0.2.dist-info/RECORD
