Metadata-Version: 2.1
Name: mediathekDownloader
Version: 1.0.2
Summary: Downloads series and movies from German public media libraries (Öffentlich-Rechtliche Sender) to your Synology NAS, for use with Synology Video Station.
Home-page: https://github.com/TomMeHo/mediathekDL
Author: Thomas Meder
Author-email: tom@tommho.net
License: BSD
Platform: UNKNOWN
Classifier: Programming Language :: Python :: 3
Classifier: License :: OSI Approved :: MIT License
Classifier: Operating System :: OS Independent
Classifier: Topic :: System :: Logging
Requires-Python: >=3.6
Requires-Dist: datetime (>=4.3)
Requires-Dist: cli-logger (>=1.0)
Requires-Dist: feedparser (>=6.0)
Requires-Dist: vsmetaEncoder (>=0.1)
Requires-Dist: wget (>=3.2)
